{
"meta":{"test_sets":[],"test_metrics":[],"learn_metrics":[{"best_value":"Min","name":"Logloss"}],"launch_mode":"Train","parameters":"","iteration_count":70,"learn_sets":["learn"],"name":"experiment"},
"iterations":[
{"learn":[0.6528797193],"iteration":0,"passed_time":0.0234559737,"remaining_time":1.618462185},
{"learn":[0.6210558518],"iteration":1,"passed_time":0.03859568009,"remaining_time":1.312253123},
{"learn":[0.5937618618],"iteration":2,"passed_time":0.05730702322,"remaining_time":1.279856852},
{"learn":[0.5725036737],"iteration":3,"passed_time":0.06962609492,"remaining_time":1.148830566},
{"learn":[0.5545604255],"iteration":4,"passed_time":0.08559701349,"remaining_time":1.112761175},
{"learn":[0.5395450672],"iteration":5,"passed_time":0.09170927435,"remaining_time":0.9782322598},
{"learn":[0.5250360871],"iteration":6,"passed_time":0.1020874386,"remaining_time":0.9187869474},
{"learn":[0.5114972016],"iteration":7,"passed_time":0.1137772963,"remaining_time":0.8817740462},
{"learn":[0.5010927054],"iteration":8,"passed_time":0.1190304376,"remaining_time":0.8067618549},
{"learn":[0.4907539426],"iteration":9,"passed_time":0.1312447492,"remaining_time":0.7874684954},
{"learn":[0.481813813],"iteration":10,"passed_time":0.1468399156,"remaining_time":0.787595911},
{"learn":[0.4736703407],"iteration":11,"passed_time":0.1603491355,"remaining_time":0.7750208216},
{"learn":[0.467034766],"iteration":12,"passed_time":0.1763601613,"remaining_time":0.7732714764},
{"learn":[0.4610676504],"iteration":13,"passed_time":0.2088200772,"remaining_time":0.8352803087},
{"learn":[0.4557008373],"iteration":14,"passed_time":0.2280446395,"remaining_time":0.836163678},
{"learn":[0.4507697744],"iteration":15,"passed_time":0.253154073,"remaining_time":0.8543949963},
{"learn":[0.4474216062],"iteration":16,"passed_time":0.2644428691,"remaining_time":0.824439533},
{"learn":[0.4441241849],"iteration":17,"passed_time":0.2736475315,"remaining_time":0.7905373131},
{"learn":[0.4394854461],"iteration":18,"passed_time":0.2936166118,"remaining_time":0.7881288002},
{"learn":[0.4354516919],"iteration":19,"passed_time":0.308646553,"remaining_time":0.7716163826},
{"learn":[0.4321437241],"iteration":20,"passed_time":0.3260501464,"remaining_time":0.760783675},
{"learn":[0.4304476184],"iteration":21,"passed_time":0.3318215039,"remaining_time":0.7239741903},
{"learn":[0.4288300068],"iteration":22,"passed_time":0.3365963536,"remaining_time":0.6878273312},
{"learn":[0.4257012208],"iteration":23,"passed_time":0.3512194376,"remaining_time":0.6731705887},
{"learn":[0.4230151471],"iteration":24,"passed_time":0.3674152084,"remaining_time":0.6613473751},
{"learn":[0.4203805024],"iteration":25,"passed_time":0.3837116148,"remaining_time":0.6493581174},
{"learn":[0.4184297735],"iteration":26,"passed_time":0.4023664959,"remaining_time":0.6408059008},
{"learn":[0.4159115245],"iteration":27,"passed_time":0.4170788734,"remaining_time":0.62561831},
{"learn":[0.414919138],"iteration":28,"passed_time":0.425630983,"remaining_time":0.6017541484},
{"learn":[0.4139240987],"iteration":29,"passed_time":0.4400183626,"remaining_time":0.5866911501},
{"learn":[0.4124409844],"iteration":30,"passed_time":0.4704943939,"remaining_time":0.591912302},
{"learn":[0.4108869165],"iteration":31,"passed_time":0.4824184596,"remaining_time":0.5728719208},
{"learn":[0.4096957599],"iteration":32,"passed_time":0.4910812561,"remaining_time":0.5506062568},
{"learn":[0.4079881445],"iteration":33,"passed_time":0.5031850459,"remaining_time":0.5327841662},
{"learn":[0.4076906138],"iteration":34,"passed_time":0.5076536401,"remaining_time":0.5076536401},
{"learn":[0.4067730817],"iteration":35,"passed_time":0.5185385644,"remaining_time":0.4897308664},
{"learn":[0.4049776681],"iteration":36,"passed_time":0.529431574,"remaining_time":0.4721957282},
{"learn":[0.4046448611],"iteration":37,"passed_time":0.5335567427,"remaining_time":0.4493109412},
{"learn":[0.4042848725],"iteration":38,"passed_time":0.5366618206,"remaining_time":0.4265773446},
{"learn":[0.4035258441],"iteration":39,"passed_time":0.5471394188,"remaining_time":0.4103545641},
{"learn":[0.4026803758],"iteration":40,"passed_time":0.5565721544,"remaining_time":0.3936729873},
{"learn":[0.4023132577],"iteration":41,"passed_time":0.5637018098,"remaining_time":0.3758012065},
{"learn":[0.4010860808],"iteration":42,"passed_time":0.5730031574,"remaining_time":0.3597926802},
{"learn":[0.4004814116],"iteration":43,"passed_time":0.5833054683,"remaining_time":0.344680504},
{"learn":[0.3997743444],"iteration":44,"passed_time":0.5950451429,"remaining_time":0.330580635},
{"learn":[0.3986117469],"iteration":45,"passed_time":0.6045054429,"remaining_time":0.3153941441},
{"learn":[0.3974665957],"iteration":46,"passed_time":0.6162763708,"remaining_time":0.3015820538},
{"learn":[0.3967461662],"iteration":47,"passed_time":0.626710419,"remaining_time":0.2872422754},
{"learn":[0.3951120639],"iteration":48,"passed_time":0.6366316702,"remaining_time":0.2728421444},
{"learn":[0.3943151748],"iteration":49,"passed_time":0.6475979461,"remaining_time":0.2590391784},
{"learn":[0.3942685717],"iteration":50,"passed_time":0.6508211994,"remaining_time":0.2424627998},
{"learn":[0.3934256614],"iteration":51,"passed_time":0.6638825114,"remaining_time":0.2298054847},
{"learn":[0.3926861204],"iteration":52,"passed_time":0.6733708003,"remaining_time":0.2159868605},
{"learn":[0.3920637291],"iteration":53,"passed_time":0.6833727635,"remaining_time":0.2024808188},
{"learn":[0.3917192439],"iteration":54,"passed_time":0.6886595619,"remaining_time":0.1878162442},
{"learn":[0.3916447423],"iteration":55,"passed_time":0.6972650038,"remaining_time":0.1743162509},
{"learn":[0.3916073803],"iteration":56,"passed_time":0.7047472152,"remaining_time":0.160731821},
{"learn":[0.391408317],"iteration":57,"passed_time":0.7104436606,"remaining_time":0.1469883436},
{"learn":[0.3904971656],"iteration":58,"passed_time":0.7205061946,"remaining_time":0.1343316634},
{"learn":[0.3901807253],"iteration":59,"passed_time":0.732506582,"remaining_time":0.1220844303},
{"learn":[0.3901595032],"iteration":60,"passed_time":0.7401780447,"remaining_time":0.1092065968},
{"learn":[0.3900910697],"iteration":61,"passed_time":0.7496406702,"remaining_time":0.09672782842},
{"learn":[0.3898446477],"iteration":62,"passed_time":0.7571058328,"remaining_time":0.08412287031},
{"learn":[0.3897719235],"iteration":63,"passed_time":0.7670021857,"remaining_time":0.07190645491},
{"learn":[0.3892543379],"iteration":64,"passed_time":0.7779591174,"remaining_time":0.05984300903},
{"learn":[0.3888101391],"iteration":65,"passed_time":0.7881547482,"remaining_time":0.04776695444},
{"learn":[0.3884365817],"iteration":66,"passed_time":0.7980454459,"remaining_time":0.03573337817},
{"learn":[0.387989966],"iteration":67,"passed_time":0.8093465477,"remaining_time":0.02380431023},
{"learn":[0.3875097996],"iteration":68,"passed_time":0.8188547297,"remaining_time":0.01186745985},
{"learn":[0.3872631636],"iteration":69,"passed_time":0.8297430276,"remaining_time":0}
]}